django_security_questions/__init__.py
django_security_questions/admin.py
django_security_questions/apps.py
django_security_questions/compat.py
django_security_questions/forms.py
django_security_questions/models.py
django_security_questions/serializers.py
django_security_questions/urls.py
django_security_questions/views.py
django_security_questions/migrations/0001_initial.py
django_security_questions/migrations/__init__.py
django_security_questions-0.1.7.dist-info/LICENSE
django_security_questions-0.1.7.dist-info/METADATA
django_security_questions-0.1.7.dist-info/WHEEL
django_security_questions-0.1.7.dist-info/top_level.txt
django_security_questions-0.1.7.dist-info/RECORD
